nttinject/Injector.py
nttinject/__init__.py
nttinject/dependency_inject.py
tests/InjectionTest.py
tests/__init__.py
ntt_injector-1.1.0.dist-info/METADATA
ntt_injector-1.1.0.dist-info/WHEEL
ntt_injector-1.1.0.dist-info/top_level.txt
ntt_injector-1.1.0.dist-info/RECORD
